{"cameraMode":{"drawMode":0,"name":"Shaded","section":"Shading Mode"},"sceneLighting":false,"audioPlay":false,"sceneViewState":{"m_AlwaysRefresh":false,"showFog":true,"showSkybox":false,"showFlares":true,"showImageEffects":true,"showParticleSystems":true,"showVisualEffectGraphs":true,"m_FxEnabled":true},"in2DMode":false,"pivot":{"x":84.03356170654297,"y":-12.102479934692383,"z":-10.265753746032715},"rotation":{"x":0.08026175200939179,"y":0.6440623998641968,"z":-0.08363562077283859,"w":0.7570592761039734},"size":58.24091720581055,"orthographic":false}